rombus/__init__.py
rombus/_core/__init__.py
rombus/_core/hdf5.py
rombus/_core/log/__init__.py
rombus/_core/log/log.py
rombus/_core/mpi.py
rombus/cli.py
rombus/ei.py
rombus/exceptions.py
rombus/model.py
rombus/models/PhenomP.py
rombus/models/PhenomP_samples.csv
rombus/models/__init__.py
rombus/models/sinc.py
rombus/models/sinc_samples.csv
rombus/params.py
rombus/plots.py
rombus/py.typed
rombus/reduced_basis.py
rombus/rom.py
rombus/samples.py
rombus/tests/__init__.py
rombus/tests/conftest.py
rombus/tests/resources/.gitignore
rombus/tests/resources/__init__.py
rombus/tests/test_PhenomP.py
rombus/tests/test_cli.py
rombus/tests/test_reduced_basis.py
rombus-1.2.3.dist-info/LICENSE
rombus-1.2.3.dist-info/METADATA
rombus-1.2.3.dist-info/WHEEL
rombus-1.2.3.dist-info/entry_points.txt
rombus-1.2.3.dist-info/RECORD
