Metadata-Version: 2.3
Name: rombus
Version: 1.2.3
Summary: Reduced order modeling for the masses
License: MIT-expat
Author: Gregory Poole
Author-email: gbpoole@gmail.com
Requires-Python: >=3.12
Classifier: License :: Other/Proprietary License
Classifier: Programming Language :: Python :: 3
Classifier: Programming Language :: Python :: 3.12
Classifier: Programming Language :: Python :: 3.13
Provides-Extra: dev
Provides-Extra: docs
Provides-Extra: mpi
Requires-Dist: Sphinx (>=6.1.3,<7.0.0) ; extra == "docs"
Requires-Dist: black (>=22.10.0,<23.0.0) ; extra == "dev"
Requires-Dist: click (>=8.1.3,<9.0.0)
Requires-Dist: h5py (>=3.8.0,<4.0.0)
Requires-Dist: matplotlib (>=3.6.2,<4.0.0)
Requires-Dist: mpi4py (>3.1.4,<4.0.0) ; extra == "mpi"
Requires-Dist: mypy (>=1.1.1,<2.0.0) ; extra == "dev"
Requires-Dist: myst-parser (>=1.0.0,<2.0.0) ; extra == "docs"
Requires-Dist: numpy (>=2.2.0)
Requires-Dist: pre-commit (>=3.0.4,<4.0.0) ; extra == "dev"
Requires-Dist: pytest (>=7.0,<8.0.0) ; extra == "dev"
Requires-Dist: pytest-cov (>=4.1.0) ; extra == "dev"
Requires-Dist: rich (>=13.3.3,<14.0.0)
Requires-Dist: ruff (>=0.0.243,<1.0.0) ; extra == "dev"
Requires-Dist: scipy (>=1.15.2)
Requires-Dist: six (>=1.16.0,<2.0.0)
Requires-Dist: sphinx-click (>=4.4.0,<5.0.0) ; extra == "docs"
Requires-Dist: sphinx-copybutton (>=0.5.1,<1.0.0) ; extra == "docs"
Requires-Dist: sphinx-rtd-theme (==1.2.0) ; extra == "docs"
